{"@context":{"@base":"http://rdf.histograph.io/","@vocab":"http://rdf.histograph.io/","features":"_:features","dataset":{"@id":"dataset","@type":"@id"},"type":{"@id":"type","@type":"@id"},"hairs":"_:hairs","relations":"_:relations","properties":"_:properties","pits":"_:pits","name":"dc:title","geometryIndex":null,"geometry":null,"data":null,"validSince":"time:hasBeginning","validUntil":"time:hasEnd"},"type":"FeatureCollection","features":[{"type":"Feature","properties":{"type":"hg:Borough","pits":[{"dataset":"cbsbuurt","type":"hg:Borough","id":"cbsbuurt/BU05990516","name":"Provenierswijk","geometryIndex":0,"hairs":[{"type":"hg:Neighbourhood","name":"Wijk 05 Noord","id":"cbswijk/WK059905","@id":"cbswijk/WK059905"}],"relations":{"hg:liesIn":[{"@id":"cbswijk/WK059905"}],"@id":"cbsbuurt/BU05990516"},"@id":"cbsbuurt/BU05990516"},{"dataset":"dbpedia","type":"hg:Borough","name":"Provenierswijk","uri":"http://dbpedia.org/resource/Provenierswijk","data":{"abstract":"De Provenierswijk is een wijk in het noorden van Rotterdam en maakt deel uit van het stadsdeel Rotterdam-Noord. In de wijk wonen 4500 mensen.De Provenierswijk dankt haar naam aan het Proveniershuis, dat aan de Schiekade stond en in 1898 werd gesloopt. Dit huis was begonnen als leprozenhuis in de 15e eeuw.De wijk wordt begrensd door de Walenburgerweg (de noordgrens met de wijk Blijdorp, de Schiekade (de oostgrens met de wijk Agniesebuurt en in het zuiden door de spoorweg door Rotterdam."},"geometryIndex":1,"relations":{"hg:sameHgConcept":[{"@id":"http://nl.dbpedia.org/resource/Provenierswijk"},{"@id":"http://wikidata.org/entity/Q7252333"},{"@id":"cbsbuurt/BU05990516"}],"@id":"http://dbpedia.org/resource/Provenierswijk"},"@id":"http://dbpedia.org/resource/Provenierswijk"}]},"geometry":{"type":"GeometryCollection","geometries":[{"type":"MultiPolygon","coordinates":[[[[4.4760286,51.9262484],[4.4740412,51.926116],[4.471953,51.9261732],[4.471363,51.9261159],[4.4712792,51.9260574],[4.4711442,51.9261249],[4.4699645,51.9259337],[4.469862,51.9260471],[4.4628733,51.9246845],[4.4625418,51.9255289],[4.4621824,51.9261638],[4.4622015,51.926261],[4.462015,51.9262108],[4.4618479,51.926595],[4.4620186,51.9265679],[4.4641527,51.9269141],[4.465834,51.9281481],[4.4668149,51.9289859],[4.4681546,51.9298711],[4.4693134,51.9307851],[4.4696451,51.9306531],[4.4762134,51.9264871],[4.4760286,51.9262484]]]]}]}}]}
