{"@context":{"@base":"http://rdf.histograph.io/","@vocab":"http://rdf.histograph.io/","features":"_:features","dataset":{"@id":"dataset","@type":"@id"},"type":{"@id":"type","@type":"@id"},"hairs":"_:hairs","relations":"_:relations","properties":"_:properties","pits":"_:pits","name":"dc:title","geometryIndex":null,"geometry":null,"data":null,"validSince":"time:hasBeginning","validUntil":"time:hasEnd"},"type":"FeatureCollection","features":[{"type":"Feature","properties":{"type":"hg:Borough","pits":[{"dataset":"cbsbuurt","type":"hg:Borough","id":"cbsbuurt/BU05991085","name":"Katendrecht","geometryIndex":0,"hairs":[{"type":"hg:Neighbourhood","name":"Wijk 10 Feijenoord","id":"cbswijk/WK059910","@id":"cbswijk/WK059910"}],"relations":{"hg:liesIn":[{"@id":"cbswijk/WK059910"}],"@id":"cbsbuurt/BU05991085"},"@id":"cbsbuurt/BU05991085"}]},"geometry":{"type":"GeometryCollection","geometries":[{"type":"MultiPolygon","coordinates":[[[[4.4797193,51.904703],[4.480322,51.9034699],[4.486212,51.9029235],[4.4940923,51.9049097],[4.4965127,51.9042993],[4.4960078,51.9021657],[4.4959859,51.9016813],[4.4960827,51.9014291],[4.4956233,51.9013967],[4.4958522,51.9012541],[4.4958306,51.9011789],[4.4959493,51.9011578],[4.4954852,51.8990453],[4.495337,51.898948],[4.4950374,51.898083],[4.4949964,51.898158],[4.4924496,51.8991688],[4.4766154,51.8957981],[4.468976,51.8985072],[4.4677614,51.9003494],[4.4697567,51.9008324],[4.4739585,51.9021415],[4.4761215,51.9029673],[4.4776194,51.9036261],[4.4797193,51.904703]]]]}]}}]}
